{
    "Ar36": {
        "error": 1.4800838935087786e-07,
        "error_type": "SEM",
        "filter_outliers_dict": {
            "filter_outliers": true,
            "iterations": 1,
            "std_devs": 2,
            "use_iqr_filtering": false,
            "use_standard_deviation_filtering": true
        },
        "fit": "parabolic",
        "fn": 990,
        "include_baseline_error": false,
        "n": 990,
        "outlier_excluded": [],
        "reviewed": true,
        "user_excluded": [],
        "value": 0.00014554594938332626
    },
    "Ar37": {
        "error": 3.3341031119685976e-07,
        "error_type": "SEM",
        "filter_outliers_dict": {
            "filter_outliers": true,
            "iterations": 1,
            "std_devs": 2,
            "use_iqr_filtering": false,
            "use_standard_deviation_filtering": true
        },
        "fit": "parabolic",
        "fn": 90,
        "include_baseline_error": false,
        "n": 90,
        "outlier_excluded": [],
        "reviewed": true,
        "user_excluded": [],
        "value": 0.00025181301988127527
    },
    "Ar38": {
        "error": 3.400572993710859e-07,
        "error_type": "SEM",
        "filter_outliers_dict": {
            "filter_outliers": true,
            "iterations": 1,
            "std_devs": 2,
            "use_iqr_filtering": false,
            "use_standard_deviation_filtering": true
        },
        "fit": "parabolic",
        "fn": 90,
        "include_baseline_error": false,
        "n": 90,
        "outlier_excluded": [],
        "reviewed": true,
        "user_excluded": [],
        "value": 0.00015246530678841285
    },
    "Ar39": {
        "error": 4.183682237978986e-06,
        "error_type": "SEM",
        "filter_outliers_dict": {
            "filter_outliers": true,
            "iterations": 1,
            "std_devs": 2,
            "use_iqr_filtering": false,
            "use_standard_deviation_filtering": true
        },
        "fit": "parabolic",
        "fn": 90,
        "include_baseline_error": false,
        "n": 90,
        "outlier_excluded": [],
        "reviewed": true,
        "user_excluded": [],
        "value": 0.009034393194498114
    },
    "Ar40": {
        "error": 2.628416073311226e-05,
        "error_type": "SEM",
        "filter_outliers_dict": {
            "filter_outliers": true,
            "iterations": 1,
            "std_devs": 2,
            "use_iqr_filtering": false,
            "use_standard_deviation_filtering": true
        },
        "fit": "parabolic",
        "fn": 71,
        "include_baseline_error": false,
        "n": 90,
        "outlier_excluded": [],
        "reviewed": true,
        "user_excluded": [],
        "value": 0.0497476549220188
    }
}